css/pomalevi.css
img/favicon.png
img/pomalevi-logo-256.png
img/splitlogo-stoplogo.pptx
img/splitlogo.png
img/stoplogo.png
pmlv/__init__.py
pmlv/args.py
pmlv/base.py
pmlv/ffmpeg.py
pmlv/html.py
pmlv/main.py
pmlv/ppt.py
poetry.lock
README.md
pomalevi-1.0.dist-info/entry_points.txt
pomalevi-1.0.dist-info/LICENSE
pomalevi-1.0.dist-info/WHEEL
pomalevi-1.0.dist-info/METADATA
pomalevi-1.0.dist-info/RECORD
