Metadata-Version: 2.1
Name: pomalevi
Version: 1.0
Summary: Powerpoint-based maintainable lecture videos
Home-page: https://github.com/prechelt/pomalevi/blob/main/README.md
License: MIT
Keywords: Powerpoint,video editing,video rendering,video player
Author: Lutz Prechelt
Author-email: prechelt@inf.fu-berlin.de
Requires-Python: >=3.8,<4.0
Classifier: Development Status :: 5 - Production/Stable
Classifier: Environment :: Console
Classifier: Environment :: Web Environment
Classifier: Intended Audience :: Education
Classifier: Intended Audience :: End Users/Desktop
Classifier: License :: OSI Approved :: MIT License
Classifier: Operating System :: Microsoft :: Windows
Classifier: Operating System :: POSIX :: Linux
Classifier: Programming Language :: Python :: 3
Classifier: Programming Language :: Python :: 3.10
Classifier: Programming Language :: Python :: 3.8
Classifier: Programming Language :: Python :: 3.9
Classifier: Topic :: Multimedia :: Video :: Conversion
Classifier: Topic :: Multimedia :: Video :: Display
Classifier: Topic :: Utilities
Requires-Dist: attrs (>=21,<22)
Requires-Dist: static-ffmpeg (>=2.2,<3.0)
Project-URL: Repository, https://github.com/prechelt/pomalevi
